django_filters_groups/__init__.py
django_filters_groups/forms.py
django_filters_groups/static/django_filters_groups/filter-defaults.js
django_filters_groups/static/django_filters_groups/filter.css
django_filters_groups/static/django_filters_groups/filter.js
django_filters_groups/templates/django_filters_groups/filters.html
django_filters_groups/templatetags/__init__.py
django_filters_groups/templatetags/django_filters_groups.py
django_filters_groups/utils.py
LICENSE
django_filter_groups-0.4.3.dist-info/LICENSE
django_filter_groups-0.4.3.dist-info/WHEEL
django_filter_groups-0.4.3.dist-info/METADATA
django_filter_groups-0.4.3.dist-info/RECORD
