Metadata-Version: 2.1
Name: django-filter-groups
Version: 0.4.3
Summary: 
Home-page: https://github.com/PNoryk/django-filter-groups
Author: pnoryk
Author-email: pnoryk@mail.ru
Requires-Python: >=3.8,<4.0
Classifier: Programming Language :: Python :: 3
Classifier: Programming Language :: Python :: 3.8
Classifier: Programming Language :: Python :: 3.9
Requires-Dist: Django (>=2)
Requires-Dist: django-filter (>=2.4.0)
Project-URL: Repository, https://github.com/PNoryk/django-filter-groups
